shipmnts_utils/__init__.py
shipmnts_utils/es_init.py
shipmnts_utils/redis_init.py
shipmnts_utils/sql_executor.py
shipmnts_utils/auth/__init__.py
shipmnts_utils/auth/auth_decorator.py
shipmnts_utils/auth/token_auth.py
shipmnts_utils/auth/token_handler.py
shipmnts_utils/firestore/__init__.py
shipmnts_utils/firestore/firestore_helper.py
shipmnts_utils/firestore/firestore_init.py
shipmnts_utils/middleware/__init__.py
shipmnts_utils/middleware/thread_local_middleware.py
shipmnts_utils/misc/__init__.py
shipmnts_utils/misc/custom_exceptions.py
shipmnts_utils/misc/download.py
shipmnts_utils/misc/utils.py
shipmnts_utils/misc/workflow_time.py
shipmnts_utils-0.0.58.dist-info/LICENSE
shipmnts_utils-0.0.58.dist-info/METADATA
shipmnts_utils-0.0.58.dist-info/WHEEL
shipmnts_utils-0.0.58.dist-info/top_level.txt
shipmnts_utils-0.0.58.dist-info/RECORD
