Metadata-Version: 2.1
Name: shipmnts-utils
Version: 0.0.58
Summary: Shipmnts Utility Functions
Home-page: https://github.com/vimox-shah/shipmnts_utils
Author: Vimox Shah
Author-email: vimox@shipmnts.com
License: UNKNOWN
Platform: UNKNOWN
Classifier: Programming Language :: Python :: 3
Classifier: License :: OSI Approved :: MIT License
Classifier: Operating System :: OS Independent
